[
	{
		"COUNT_TABLE":999,
		"TABLENAME":"PER_PERSONAL",
		"LIST_COLUMN":[ 
			{"column_name":"PER_ID","data_type":"NUMBER","data_length":"22","data_precision":"10","data_scale":"0"} ,	
			{"column_name":"PER_TYPE","data_type":"NUMBER","data_length":"22","data_precision":"1","data_scale":"0"} ,
			{"column_name":"OT_CODE","data_type":"CHAR","data_length":"10","data_precision":"","data_scale":""} ,	
			{"column_name":"PN_CODE","data_type":"CHAR","data_length":"3","data_precision":"","data_scale":""} ,	
			{"column_name":"PER_NAME","data_type":"VARCHAR2","data_length":"100","data_precision":"","data_scale":""} ,	
			{"column_name":"PER_SURNAME","data_type":"VARCHAR2","data_length":"100","data_precision":"","data_scale":""} ,	
			{"column_name":"PER_ENG_NAME","data_type":"VARCHAR2","data_length":"100","data_precision":"","data_scale":""} ,	
			{"column_name":"PER_ENG_SURNAME","data_type":"VARCHAR2","data_length":"50","data_precision":"","data_scale":""} ,	
			{"column_name":"ORG_ID","data_type":"NUMBER","data_length":"22","data_precision":"10","data_scale":"0"} ,	
			{"column_name":"POS_ID","data_type":"NUMBER","data_length":"22","data_precision":"10","data_scale":"0"} ,	
			{"column_name":"POEM_ID","data_type":"NUMBER","data_length":"22","data_precision":"10","data_scale":"0"} ,	
			{"column_name":"LEVEL_NO","data_type":"CHAR","data_length":"2","data_precision":"","data_scale":""} ,	
			{"column_name":"PER_ORGMGT","data_type":"NUMBER","data_length":"22","data_precision":"1","data_scale":"0"} ,	
			{"column_name":"PER_SALARY","data_type":"NUMBER","data_length":"22","data_precision":"16","data_scale":"2"} ,	
			{"column_name":"PER_MGTSALARY","data_type":"NUMBER","data_length":"22","data_precision":"16","data_scale":"2"} ,	
			{"column_name":"PER_SPSALARY","data_type":"NUMBER","data_length":"22","data_precision":"16","data_scale":"2"} ,	
			{"column_name":"PER_GENDER","data_type":"NUMBER","data_length":"22","data_precision":"1","data_scale":"0"} ,	
			{"column_name":"MR_CODE","data_type":"CHAR","data_length":"2","data_precision":"","data_scale":""} ,	
			{"column_name":"PER_CARDNO","data_type":"CHAR","data_length":"13","data_precision":"","data_scale":""} ,	
			{"column_name":"PER_OFFNO","data_type":"CHAR","data_length":"20","data_precision":"","data_scale":""} ,	
			{"column_name":"PER_TAXNO","data_type":"VARCHAR2","data_length":"13","data_precision":"","data_scale":""} ,	
			{"column_name":"PER_BLOOD","data_type":"CHAR","data_length":"5","data_precision":"","data_scale":""} ,	
			{"column_name":"RE_CODE","data_type":"CHAR","data_length":"2","data_precision":"","data_scale":""} ,	
			{"column_name":"PER_BIRTHDATE","data_type":"CHAR","data_length":"19","data_precision":"","data_scale":""} ,	
			{"column_name":"PER_RETIREDATE","data_type":"CHAR","data_length":"19","data_precision":"","data_scale":""} ,	
			{"column_name":"PER_STARTDATE","data_type":"CHAR","data_length":"19","data_precision":"","data_scale":""} ,	
			{"column_name":"PER_OCCUPYDATE","data_type":"CHAR","data_length":"19","data_precision":"","data_scale":""} ,	
			{"column_name":"PER_POSDATE","data_type":"CHAR","data_length":"19","data_precision":"","data_scale":""} ,	
			{"column_name":"PER_SALDATE","data_type":"CHAR","data_length":"19","data_precision":"","data_scale":""} ,	
			{"column_name":"PN_CODE_F","data_type":"CHAR","data_length":"3","data_precision":"","data_scale":""} ,	
			{"column_name":"PER_FATHERNAME","data_type":"VARCHAR2","data_length":"100","data_precision":"","data_scale":""} ,	
			{"column_name":"PER_FATHERSURNAME","data_type":"VARCHAR2","data_length":"100","data_precision":"","data_scale":""} ,	
			{"column_name":"PN_CODE_M","data_type":"CHAR","data_length":"3","data_precision":"","data_scale":""} ,	
			{"column_name":"PER_MOTHERNAME","data_type":"VARCHAR2","data_length":"100","data_precision":"","data_scale":""} ,	
			{"column_name":"PER_MOTHERSURNAME","data_type":"VARCHAR2","data_length":"100","data_precision":"","data_scale":""} ,	
			{"column_name":"PER_ADD1","data_type":"VARCHAR2","data_length":"200","data_precision":"","data_scale":""} ,	
			{"column_name":"PER_ADD2","data_type":"VARCHAR2","data_length":"200","data_precision":"","data_scale":""} ,	
			{"column_name":"PV_CODE","data_type":"CHAR","data_length":"10","data_precision":"","data_scale":""} ,	
			{"column_name":"MOV_CODE","data_type":"CHAR","data_length":"10","data_precision":"","data_scale":""} ,	
			{"column_name":"PER_ORDAIN","data_type":"NUMBER","data_length":"22","data_precision":"1","data_scale":"0"} ,	
			{"column_name":"PER_SOLDIER","data_type":"NUMBER","data_length":"22","data_precision":"1","data_scale":"0"} ,	
			{"column_name":"PER_MEMBER","data_type":"NUMBER","data_length":"22","data_precision":"1","data_scale":"0"} ,	
			{"column_name":"PER_STATUS","data_type":"NUMBER","data_length":"22","data_precision":"10","data_scale":"0"} ,	
			{"column_name":"UPDATE_USER","data_type":"NUMBER","data_length":"22","data_precision":"11","data_scale":"0"} ,
			{"column_name":"UPDATE_DATE","data_type":"CHAR","data_length":"19","data_precision":"","data_scale":""} ,	
			{"column_name":"DEPARTMENT_ID","data_type":"NUMBER","data_length":"22","data_precision":"10","data_scale":"0"} ,	
			{"column_name":"APPROVE_PER_ID","data_type":"NUMBER","data_length":"22","data_precision":"10","data_scale":"0"} ,	
			{"column_name":"REPLACE_PER_ID","data_type":"NUMBER","data_length":"22","data_precision":"10","data_scale":"0"} ,	
			{"column_name":"ABSENT_FLAG","data_type":"NUMBER","data_length":"22","data_precision":"1","data_scale":"0"} ,	
			{"column_name":"POEMS_ID","data_type":"NUMBER","data_length":"22","data_precision":"10","data_scale":"0"} ,	
			{"column_name":"PER_HIP_FLAG","data_type":"VARCHAR2","data_length":"20","data_precision":"","data_scale":""} ,	
			{"column_name":"PER_CERT_OCC","data_type":"VARCHAR2","data_length":"100","data_precision":"","data_scale":""} ,	
			{"column_name":"LEVEL_NO_SALARY","data_type":"VARCHAR2","data_length":"10","data_precision":"","data_scale":""} ,	
			{"column_name":"PER_NICKNAME","data_type":"VARCHAR2","data_length":"20","data_precision":"","data_scale":""} ,	
			{"column_name":"PER_HOME_TEL","data_type":"VARCHAR2","data_length":"20","data_precision":"","data_scale":""} ,	
			{"column_name":"PER_OFFICE_TEL","data_type":"VARCHAR2","data_length":"30","data_precision":"","data_scale":""} ,	
			{"column_name":"PER_FAX","data_type":"VARCHAR2","data_length":"20","data_precision":"","data_scale":""} ,	
			{"column_name":"PER_MOBILE","data_type":"VARCHAR2","data_length":"20","data_precision":"","data_scale":""} ,	
			{"column_name":"PER_EMAIL","data_type":"VARCHAR2","data_length":"100","data_precision":"","data_scale":""} ,	
			{"column_name":"PER_FILE_NO","data_type":"VARCHAR2","data_length":"25","data_precision":"","data_scale":""} ,	
			{"column_name":"PER_BANK_ACCOUNT","data_type":"VARCHAR2","data_length":"25","data_precision":"","data_scale":""} ,	
			{"column_name":"PER_ID_REF","data_type":"NUMBER","data_length":"22","data_precision":"10","data_scale":"0"} ,	
			{"column_name":"PER_ID_ASS_REF","data_type":"NUMBER","data_length":"22","data_precision":"10","data_scale":"0"} ,	
			{"column_name":"PER_CONTACT_PERSON","data_type":"VARCHAR2","data_length":"2000","data_precision":"","data_scale":""} ,	
			{"column_name":"PER_REMARK","data_type":"VARCHAR2","data_length":"2000","data_precision":"","data_scale":""} ,	
			{"column_name":"PER_START_ORG","data_type":"VARCHAR2","data_length":"255","data_precision":"","data_scale":""} ,	
			{"column_name":"PER_COOPERATIVE","data_type":"NUMBER","data_length":"22","data_precision":"1","data_scale":"0"} ,	
			{"column_name":"PER_COOPERATIVE_NO","data_type":"VARCHAR2","data_length":"25","data_precision":"","data_scale":""} ,	
			{"column_name":"PER_MEMBERDATE","data_type":"VARCHAR2","data_length":"19","data_precision":"","data_scale":""} ,	
			{"column_name":"PER_SEQ_NO","data_type":"NUMBER","data_length":"22","data_precision":"5","data_scale":"0"} ,	
			{"column_name":"PAY_ID","data_type":"NUMBER","data_length":"22","data_precision":"10","data_scale":"0"} ,	
			{"column_name":"ES_CODE","data_type":"VARCHAR2","data_length":"10","data_precision":"","data_scale":""} ,	
			{"column_name":"PL_NAME_WORK","data_type":"VARCHAR2","data_length":"255","data_precision":"","data_scale":""} ,	
			{"column_name":"ORG_NAME_WORK","data_type":"VARCHAR2","data_length":"255","data_precision":"","data_scale":""} ,	
			{"column_name":"PER_DOCNO","data_type":"VARCHAR2","data_length":"255","data_precision":"","data_scale":""} ,	
			{"column_name":"PER_DOCDATE","data_type":"VARCHAR2","data_length":"19","data_precision":"","data_scale":""} ,	
			{"column_name":"PER_EFFECTIVEDATE","data_type":"VARCHAR2","data_length":"19","data_precision":"","data_scale":""} ,	
			{"column_name":"PER_POS_REASON","data_type":"VARCHAR2","data_length":"255","data_precision":"","data_scale":""} ,	
			{"column_name":"PER_POS_YEAR","data_type":"VARCHAR2","data_length":"4","data_precision":"","data_scale":""} ,	
			{"column_name":"PER_POS_DOCTYPE","data_type":"VARCHAR2","data_length":"255","data_precision":"","data_scale":""} ,	
			{"column_name":"PER_POS_DOCNO","data_type":"VARCHAR2","data_length":"255","data_precision":"","data_scale":""} ,	
			{"column_name":"PER_POS_ORG","data_type":"VARCHAR2","data_length":"255","data_precision":"","data_scale":""} ,
			{"column_name":"PER_ORDAIN_DETAIL","data_type":"VARCHAR2","data_length":"255","data_precision":"","data_scale":""} ,	
			{"column_name":"PER_POS_ORGMGT","data_type":"VARCHAR2","data_length":"255","data_precision":"","data_scale":""} ,	
			{"column_name":"PER_POS_DOCDATE","data_type":"VARCHAR2","data_length":"19","data_precision":"","data_scale":""} ,	
			{"column_name":"PER_POS_DESC","data_type":"VARCHAR2","data_length":"255","data_precision":"","data_scale":""} ,	
			{"column_name":"PER_POS_REMARK","data_type":"VARCHAR2","data_length":"255","data_precision":"","data_scale":""} ,	
			{"column_name":"PER_BOOK_NO","data_type":"VARCHAR2","data_length":"255","data_precision":"","data_scale":""} ,	
			{"column_name":"PER_BOOK_DATE","data_type":"VARCHAR2","data_length":"19","data_precision":"","data_scale":""} ,	
			{"column_name":"PER_CONTACT_COUNT","data_type":"NUMBER","data_length":"22","data_precision":"2","data_scale":"0"} ,	
			{"column_name":"PER_DISABILITY","data_type":"NUMBER","data_length":"22","data_precision":"1","data_scale":"0"} ,	
			{"column_name":"POT_ID","data_type":"NUMBER","data_length":"22","data_precision":"10","data_scale":"0"} ,	
			{"column_name":"PER_UNION","data_type":"NUMBER","data_length":"22","data_precision":"1","data_scale":"0"} ,	
			{"column_name":"PER_UNIONDATE","data_type":"VARCHAR2","data_length":"19","data_precision":"","data_scale":""} ,	
			{"column_name":"PER_JOB","data_type":"VARCHAR2","data_length":"2000","data_precision":"","data_scale":""} ,	
			{"column_name":"ORG_ID_1","data_type":"NUMBER","data_length":"22","data_precision":"10","data_scale":"0"} ,	
			{"column_name":"ORG_ID_2","data_type":"NUMBER","data_length":"22","data_precision":"10","data_scale":"0"} ,	
			{"column_name":"ORG_ID_3","data_type":"NUMBER","data_length":"22","data_precision":"10","data_scale":"0"} ,	
			{"column_name":"ORG_ID_4","data_type":"NUMBER","data_length":"22","data_precision":"10","data_scale":"0"} ,	
			{"column_name":"ORG_ID_5","data_type":"NUMBER","data_length":"22","data_precision":"10","data_scale":"0"} ,	
			{"column_name":"PER_UNION2","data_type":"NUMBER","data_length":"22","data_precision":"1","data_scale":"0"} ,	
			{"column_name":"PER_UNIONDATE2","data_type":"VARCHAR2","data_length":"19","data_precision":"","data_scale":""} ,	
			{"column_name":"PER_UNION3","data_type":"NUMBER","data_length":"22","data_precision":"1","data_scale":"0"} ,	
			{"column_name":"PER_UNIONDATE3","data_type":"VARCHAR2","data_length":"19","data_precision":"","data_scale":""} ,	
			{"column_name":"PER_UNION4","data_type":"NUMBER","data_length":"22","data_precision":"1","data_scale":"0"} ,	
			{"column_name":"PER_UNIONDATE4","data_type":"VARCHAR2","data_length":"19","data_precision":"","data_scale":""} ,	
			{"column_name":"PER_UNION5","data_type":"NUMBER","data_length":"22","data_precision":"1","data_scale":"0"} ,	
			{"column_name":"PER_UNIONDATE5","data_type":"VARCHAR2","data_length":"19","data_precision":"","data_scale":""} ,	
			{"column_name":"PER_SET_ASS","data_type":"NUMBER","data_length":"22","data_precision":"1","data_scale":"0"} ,	
			{"column_name":"PER_AUDIT_FLAG","data_type":"NUMBER","data_length":"22","data_precision":"1","data_scale":"0"} ,	
			{"column_name":"PER_PROBATION_FLAG","data_type":"NUMBER","data_length":"22","data_precision":"1","data_scale":"0"} ,	
			{"column_name":"DEPARTMENT_ID_ASS","data_type":"NUMBER","data_length":"22","data_precision":"10","data_scale":"0"} ,	
			{"column_name":"PER_BIRTH_PLACE","data_type":"VARCHAR2","data_length":"100","data_precision":"","data_scale":""} ,	
			{"column_name":"PER_FLAW","data_type":"VARCHAR2","data_length":"100","data_precision":"","data_scale":""} ,	
			{"column_name":"PER_SCAR","data_type":"VARCHAR2","data_length":"100","data_precision":"","data_scale":""} ,	
			{"column_name":"PER_RENEW","data_type":"NUMBER","data_length":"22","data_precision":"1","data_scale":"0"} ,	
			{"column_name":"PER_LEVELDATE","data_type":"VARCHAR2","data_length":"19","data_precision":"","data_scale":""} ,	
			{"column_name":"PER_POSTDATE","data_type":"VARCHAR2","data_length":"19","data_precision":"","data_scale":""} ,	
			{"column_name":"PER_OT_FLAG","data_type":"NUMBER","data_length":"22","data_precision":"10","data_scale":"0"} 
		]
	}
]